dj_bootstrap_swatches/__init__.py
dj_bootstrap_swatches/apps.py
dj_bootstrap_swatches/models.py
dj_bootstrap_swatches/urls.py
dj_bootstrap_swatches/views.py
dj_bootstrap_swatches/static/css/dj_bootstrap_swatches.css
dj_bootstrap_swatches/static/js/dj_bootstrap_swatches.js
dj_bootstrap_swatches/templates/dj_bootstrap_swatches/3.html
dj_bootstrap_swatches/templates/dj_bootstrap_swatches/base.html
dj_bootstrap_swatches-0.6.0.dist-info/DESCRIPTION.rst
dj_bootstrap_swatches-0.6.0.dist-info/METADATA
dj_bootstrap_swatches-0.6.0.dist-info/RECORD
dj_bootstrap_swatches-0.6.0.dist-info/WHEEL
dj_bootstrap_swatches-0.6.0.dist-info/metadata.json
dj_bootstrap_swatches-0.6.0.dist-info/top_level.txt
