Metadata-Version: 2.0
Name: dj-bootstrap-swatches
Version: 0.6.0
Summary: A swatch page for Bootstrap styling
Home-page: https://github.com/bwarren2/dj-bootstrap-swatches
Author: Ben Warren
Author-email: ben@maaina.com
License: MIT
Keywords: dj-bootstrap-swatches
Platform: UNKNOWN
Classifier: Development Status :: 3 - Alpha
Classifier: Framework :: Django
Classifier: Framework :: Django :: 1.8
Classifier: Framework :: Django :: 1.9
Classifier: Framework :: Django :: 1.10
Classifier: Intended Audience :: Developers
Classifier: License :: OSI Approved :: BSD License
Classifier: Natural Language :: English
Classifier: Programming Language :: Python :: 2
Classifier: Programming Language :: Python :: 2.7
Classifier: Programming Language :: Python :: 3
Classifier: Programming Language :: Python :: 3.3
Classifier: Programming Language :: Python :: 3.4
Classifier: Programming Language :: Python :: 3.5
